xyz_eventlog/__init__.py
xyz_eventlog/apis.py
xyz_eventlog/apps.py
xyz_eventlog/models.py
xyz_eventlog/receivers.py
xyz_eventlog/serializers.py
xyz_eventlog/signals.py
xyz_eventlog/migrations/0001_initial.py
xyz_eventlog/migrations/__init__.py
xyz_eventlog-0.0.2.dist-info/METADATA
xyz_eventlog-0.0.2.dist-info/WHEEL
xyz_eventlog-0.0.2.dist-info/top_level.txt
xyz_eventlog-0.0.2.dist-info/RECORD
